miniutils/__init__.py
miniutils/capture_output.py
miniutils/logs.py
miniutils/logs_base.py
miniutils/magic_contract.py
miniutils/opt_decorator.py
miniutils/progress_bar.py
miniutils/py2_template.py
miniutils/py2_wrap.py
miniutils/timing.py
miniutils/caching/__init__.py
miniutils/caching/file_call.py
miniutils/caching/indexable.py
miniutils/caching/property.py
miniutils-1.0.3.dist-info/LICENSE
miniutils-1.0.3.dist-info/METADATA
miniutils-1.0.3.dist-info/WHEEL
miniutils-1.0.3.dist-info/top_level.txt
miniutils-1.0.3.dist-info/RECORD
