Metadata-Version: 2.1
Name: miniutils
Version: 1.0.3
Summary: Small Python utilities for adding concise functionality and usability to your code
Home-page: http://miniutils.readthedocs.io/en/latest/
Author: scnerd
Author-email: scnerd@gmail.com
License: MIT
Download-URL: https://github.com/scnerd/miniutils
Keywords: miniutils,utilities,decorators,minimal
Platform: UNKNOWN
Requires-Python: >=3
Requires-Dist: tqdm
Requires-Dist: pycontracts
Requires-Dist: coloredlogs
